[{"id":1,"name":"PERSON","color":"red-11"},{"id":5,"name":"ORG","color":"pink-11"},{"id":6,"name":"GPE","color":"light-blue-11"},{"id":8,"name":"PRODUCT","color":"brown-11"},{"id":13,"name":"DATE","color":"deep-purple-11"},{"id":14,"name":"TIME","color":"teal-11"},{"id":17,"name":"QUANTITY","color":"indigo-11"},{"id":19,"name":"CARDINAL","color":"orange-11"},{"id":20,"name":"DRUG","color":"red-11"},{"id":21,"name":"DOSAGE","color":"blue-11"},{"id":22,"name":"DURATION","color":"light-green-11"},{"id":23,"name":"FREQUENCY","color":"deep-orange-11"},{"id":24,"name":"ROUTE","color":"pink-11"}]